matplotlibqml/__init__.py
matplotlibqml/demoview.qml
matplotlibqml/matplotlibqml.py
matplotlibqml/widgetdemo.py
matplotlibqml-0.92.2.dist-info/LICENSE
matplotlibqml-0.92.2.dist-info/METADATA
matplotlibqml-0.92.2.dist-info/WHEEL
matplotlibqml-0.92.2.dist-info/top_level.txt
matplotlibqml-0.92.2.dist-info/RECORD
