Metadata-Version: 2.1
Name: matplotlibqml
Version: 0.92.2
Summary: Matplotlib Mini QML Backend
Home-page: https://github.com/medlab/matplotlibqml
Author: Cong Zhang
Author-email: congzhangzh@gmail.com
Maintainer: Cong Zhang
Maintainer-email: congzhangzh@gmail.com
License: UNKNOWN
Platform: UNKNOWN
Classifier: License :: OSI Approved :: MIT License
Classifier: Programming Language :: Python :: 3
Classifier: Operating System :: OS Independent
Requires-Dist: PySide6
Requires-Dist: matplotlib
